fastapi_ltfi_wsap/__init__.py
fastapi_ltfi_wsap/app.py
fastapi_ltfi_wsap/config.py
fastapi_ltfi_wsap/dependencies.py
fastapi_ltfi_wsap/middleware.py
fastapi_ltfi_wsap/models.py
fastapi_ltfi_wsap/routers.py
fastapi_ltfi_wsap-2.0.0.dist-info/licenses/LICENSE
fastapi_ltfi_wsap-2.0.0.dist-info/licenses/NOTICE
fastapi_ltfi_wsap-2.0.0.dist-info/METADATA
fastapi_ltfi_wsap-2.0.0.dist-info/WHEEL
fastapi_ltfi_wsap-2.0.0.dist-info/top_level.txt
fastapi_ltfi_wsap-2.0.0.dist-info/RECORD
