Metadata-Version: 2.4
Name: fastapi-ltfi-wsap
Version: 2.0.0
Summary: FastAPI integration for LTFI-WSAP (Layered Transformer Framework Intelligence - Web System Alignment Protocol) by Kief Studio
Home-page: https://github.com/Kief-Studio/fastapi-ltfi-wsap
Author: Kief Studio
Author-email: Kief Studio <developers@kief.studio>
Maintainer-email: Kief Studio <developers@kief.studio>
License: MIT
Project-URL: Documentation, https://fastapi-ltfi-wsap.readthedocs.io
Project-URL: Repository, https://github.com/KiefStudioMA/LTFI-WSAP-FastAPI
Project-URL: Bug Reports, https://github.com/KiefStudioMA/LTFI-WSAP-FastAPI/issues
Project-URL: Company, https://kief.studio
Project-URL: LTFI Ecosystem, https://ltfi.ai
Project-URL: WSAP Protocol, https://wsap.ltfi.ai
Keywords: fastapi,wsap,ltfi,verification,domain,security,api,integration,kief-studio
Classifier: Development Status :: 5 - Production/Stable
Classifier: Intended Audience :: Developers
Classifier: Topic :: Software Development :: Libraries :: Python Modules
Classifier: Topic :: Internet :: WWW/HTTP
Classifier: Topic :: Internet :: WWW/HTTP :: Dynamic Content
Classifier: Framework :: FastAPI
Classifier: License :: OSI Approved :: MIT License
Classifier: Programming Language :: Python :: 3
Classifier: Programming Language :: Python :: 3.8
Classifier: Programming Language :: Python :: 3.9
Classifier: Programming Language :: Python :: 3.10
Classifier: Programming Language :: Python :: 3.11
Classifier: Programming Language :: Python :: 3.12
Classifier: Operating System :: OS Independent
Requires-Python: >=3.8
License-File: LICENSE
License-File: NOTICE
Requires-Dist: fastapi>=0.68.0
Requires-Dist: ltfi-wsap-sdk>=2.0.0
Requires-Dist: pydantic>=2.0.0
Provides-Extra: dev
Requires-Dist: pytest>=7.0.0; extra == "dev"
Requires-Dist: pytest-asyncio>=0.21.0; extra == "dev"
Requires-Dist: pytest-cov>=4.0.0; extra == "dev"
Requires-Dist: httpx>=0.24.0; extra == "dev"
Requires-Dist: black>=23.0.0; extra == "dev"
Requires-Dist: ruff>=0.1.0; extra == "dev"
Requires-Dist: mypy>=1.0.0; extra == "dev"
Dynamic: author
Dynamic: home-page
Dynamic: license-file
Dynamic: requires-python
